MANIFEST.in
README.rst
setup.cfg
setup.py
argutil/__init__.py
argutil/argutil.py
argutil/commandline.schema
argutil/deepcopy.py
argutil/defaults.py
argutil/primitives.py
argutil/template.py
argutil/working_directory.py
argutil.egg-info/PKG-INFO
argutil.egg-info/SOURCES.txt
argutil.egg-info/dependency_links.txt
argutil.egg-info/requires.txt
argutil.egg-info/top_level.txt
tests/__init__.py
tests/deepcopy_test.py
tests/defaults_file_test.py
tests/definitions_file_test.py
tests/get_parser_test.py
tests/helper.py
tests/module_creation_test.py
tests/submodules_test.py
tests/template_test.py
tests/working_directory_test.py