Metadata-Version: 1.0
Name: argutil
Version: 1.1.6
Summary: Wrapper for argparse that uses JSON config files to define command line parsers
Home-page: http://github.com/cmccandless/argutil
Author: cmccandless
Author-email: UNKNOWN
License: UNKNOWN
Keywords: commandline,json
Platform: UNKNOWN
